Workbook
Name Awards_Rewards_and_Prizes: links!$K$84:$K$86
Name CO: links!$B$2:$B$3
Name Communication_Expenses: links!$K$79:$K$83
Name Confidential__Intelligence_and_Extraordinary_Expenses: links!$K$93
Name Demolition_Relocation_and_Desilting_Dredging_Expenses: links!$K$90
Name Financial_Assistance_Subsidy: links!$K$157:$K$163
Name General_Services: links!$K$99:$K$103
Name Generation__Transmission_and_Distribution_Expenses: links!$K$91:$K$92
Name Intangible_Assets_Outlay: links!$K$220:$K$222
Name Labor_and_Wages: links!$K$168
Name MOOE: links!$B$4:$B$20
Name Other_Compensation: links!$K$4:$K$25
Name Other_Maintenance_and_Operating_Expenses: links!$K$169:$K$191
Name Other_Personnel_Benefits: links!$K$30:$K$41
Name Personnel_Benefit_Contributions: links!$K$26:$K$29
Name Professional_Services: links!$K$94:$K$98
Name Property__Plant_and_Equipment_Outlay: links!$K$192:$K$219
Name PS: links!$B$21:$B$24
Name Repairs_and_Maintenance: links!$K$104:$K$156
Name Salaries_and_Wages: links!$K$2:$K$3
Name Supplies_and_Materials_Expenses: links!$K$47:$K$76
Name Survey__Research__Exploration_and_Development_Expenses: links!$K$87:$K$89
Name Taxes__Insurance_Premiums_and_Other_Fees: links!$K$164:$K$167
Name Training_and_Scholarship_Expenses: links!$K$44:$K$46
Name Traveling_Expenses: links!$K$42:$K$43
Name Utility_Expenses: links!$K$77:$K$78

Sheet Expenditure Form
A1: Department of Education
A3: Office Code : | B3: 302709 | BU3: 302709
A4: Office Name : | B4: Luis Hervias National High School
A5: Fiscal Year : | B5: 2026
A7: =CONCATENATE("FY ",B5," EXPENDITURE FORM") -> FY 2026 EXPENDITURE FORM
A9: PAP | B9: KRA | C9: Specific Program | D9: Output | E9: Output Priority Rank | F9: Output Milestone | G9: Activities | H9: Performance Indicator | I9: Expense Class (PS /MOOE/ CO) | J9: Expense Object DBM Grouping | L9: GAA by Object | N9: Expense Item | O9: COSTING | S9: Location for TEV | T9: PPMP (Y/N) | U9: APP-Supplies (Y/N) | V9: APP-Airline Ticket (Y/N) | W9: Manner of Release (Downloading, Cash Advance, Direct Payment) | X9: =CONCATENATE("FY ",B5-1," Physical Target") -> FY 2025 Physical Target | AE9: =CONCATENATE("FY ",B5," Physical Target") -> FY 2026 Physical Target | AR9: =CONCATENATE("FY ",B5," FINANCIAL OBLIGATION PROGRAM") -> FY 2026 FINANCIAL OBLIGATION PROGRAM | BE9: =CONCATENATE("FY ",B5," FINANCIAL DISBURSEMENT PROGRAM") -> FY 2026 FINANCIAL DISBURSEMENT PROGRAM | BR9: =CONCATENATE("FY ",B5+1," FINANCIAL DISBURSEMENT PROGRAM") -> FY 2027 FINANCIAL DISBURSEMENT PROGRAM | BV9: For Clearance Review
O10: Quantity | P10: Unit Cost | Q10: Frequency | R10: Total Amount | X10: Total Physical Target | Y10: Q3 | AB10: Q4 | AE10: Total Physical Target | AF10: Q1 | AI10: Q2 | AL10: Q3 | AO10: Q4 | AR10: Total Obligation | AS10: Q1 | AV10: Q2 | AY10: Q3 | BB10: Q4 | BE10: Total Disbursement | BF10: Q1 | BI10: Q2 | BL10: Q3 | BO10: Q4 | BR10: Total Disbursement | BS10: Q1
Y11: July | Z11: Aug. | AA11: Sept. | AB11: Oct. | AC11: Nov. | AD11: Dec. | AF11: Jan. | AG11: Feb. | AH11: Mar. | AI11: Apr. | AJ11: May | AK11: June | AL11: July | AM11: Aug. | AN11: Sept. | AO11: Oct. | AP11: Nov. | AQ11: Dec. | AS11: Jan. | AT11: Feb. | AU11: Mar. | AV11: Apr. | AW11: May | AX11: June | AY11: July | AZ11: Aug. | BA11: Sept. | BB11: Oct. | BC11: Nov. | BD11: Dec. | BF11: Jan. | BG11: Feb. | BH11: Mar. | BI11: Apr. | BJ11: May | BK11: June | BL11: July | BM11: Aug. | BN11: Sept. | BO11: Oct. | BP11: Nov. | BQ11: Dec. | BS11: Jan. | BT11: Feb. | BU11: Mar.
A12: 310400100003000 - Operation of Schools - Junior High School (Grade 7 to Grade 10) (Total Budget Cost :3,085,000.00) | BW12: 69 | BX12: 71127 | BY12: 2026
C13: Pillar 5:Monitoring and evaluation processes and tools | K13: =VLOOKUP(J13,links!B$2:C$24,2,FALSE) -> #N/A | BY13: =IF(ISBLANK(C13),0,1) -> 1 | BZ13: =IF(ISBLANK(D13),0,1) -> 0 | CA13: =IF(ISBLANK(F13),0,1) -> 0 | CB13: =IF(ISBLANK(G13),0,1) -> 0 | CC13: =IF(ISBLANK(N13),0,1) -> 0
D14: Submitted SMEA reports | E14: 1 | H14: No. of SMEA reports submitted | K14: =VLOOKUP(J14,links!B$2:C$24,2,FALSE) -> #N/A | X14: =SUM(Y14:AD14) -> 0 | AE14: =SUM(AF14:AQ14) -> 4 | AH14: 1 | AK14: 1 | AN14: 1 | AQ14: 1 | BY14: =IF(ISBLANK(C14),0,1) -> 0 | BZ14: =IF(ISBLANK(D14),0,1) -> 1 | CA14: =IF(ISBLANK(F14),0,1) -> 0 | CB14: =IF(ISBLANK(G14),0,1) -> 0 | CC14: =IF(ISBLANK(N14),0,1) -> 0
G15: Conduct Execom Meeting | H15: No. of Execom meeting conducted | K15: =VLOOKUP(J15,links!B$2:C$24,2,FALSE) -> #N/A | R15: =R16 -> 10000 | X15: =SUM(Y15:AD15) -> 0 | AE15: =SUM(AF15:AQ15) -> 4 | AH15: 1 | AK15: 1 | AN15: 1 | AQ15: 1 | AR15: =AR16 -> 10000 | AS15: =AS16 -> 0 | AT15: =AT16 -> 0 | AU15: =AU16 -> 2500 | AV15: =AV16 -> 0 | AW15: =AW16 -> 0 | AX15: =AX16 -> 2500 | AY15: =AY16 -> 0 | ... BQ15: =BQ16 -> 2500 | BY15: =IF(ISBLANK(C15),0,1) -> 0 | BZ15: =IF(ISBLANK(D15),0,1) -> 0 | CA15: =IF(ISBLANK(F15),0,1) -> 0 | CB15: =IF(ISBLANK(G15),0,1) -> 1 | CC15: =IF(ISBLANK(N15),0,1) -> 0
I16: MOOE | J16: Training and Scholarship Expenses | K16: =VLOOKUP(J16,[1]links!B$2:C$24,2,FALSE) -> Training_and_Scholarship_Expenses | L16: Training Expenses | M16: =VLOOKUP(L16,[1]links!K$2:L$222,2,FALSE) -> 44 | N16: snacks for the conduct of Execom Meeting | O16: 1 | P16: 2500 | Q16: 4 | R16: =O16*P16*Q16 -> 10000 | T16: Y | U16: N | V16: N | W16: Direct Payment | AR16: =SUM(AS16:BD16) -> 10000 | AU16: 2500 | AX16: 2500 | BA16: 2500 | BD16: 2500 | BE16: =SUM(BF16:BQ16) -> 10000 | BH16: 2500 | BK16: 2500 | BN16: 2500 | BQ16: 2500 | BY16: =IF(ISBLANK(C16),0,1) -> 0 | BZ16: =IF(ISBLANK(D16),0,1) -> 0 | CA16: =IF(ISBLANK(F16),0,1) -> 0 | CB16: =IF(ISBLANK(G16),0,1) -> 0 | CC16: =IF(ISBLANK(N16),0,1) -> 1
G17: Conduct SMEA presentation | H17: No. of SMEA presentation conducted | K17: =VLOOKUP(J17,links!B$2:C$24,2,FALSE) -> #N/A | R17: =R18 -> 20000 | X17: =SUM(Y17:AD17) -> 0 | AE17: =SUM(AF17:AQ17) -> 4 | AH17: 1 | AK17: 1 | AN17: 1 | AQ17: 1 | AR17: =AR18 -> 20000 | AS17: =AS18 -> 0 | AT17: =AT18 -> 0 | AU17: =AU18 -> 5000 | AV17: =AV18 -> 0 | AW17: =AW18 -> 0 | AX17: =AX18 -> 5000 | AY17: =AY18 -> 0 | ... BQ17: =BQ18 -> 5000 | BY17: =IF(ISBLANK(C17),0,1) -> 0 | BZ17: =IF(ISBLANK(D17),0,1) -> 0 | CA17: =IF(ISBLANK(F17),0,1) -> 0 | CB17: =IF(ISBLANK(G17),0,1) -> 1 | CC17: =IF(ISBLANK(N17),0,1) -> 0
I18: MOOE | J18: Training and Scholarship Expenses | K18: =VLOOKUP(J18,[1]links!B$2:C$24,2,FALSE) -> Training_and_Scholarship_Expenses | L18: Training Expenses | M18: =VLOOKUP(L18,[1]links!K$2:L$222,2,FALSE) -> 44 | N18: snacks for the conduct of SMEA presentation | O18: 1 | P18: 5000 | Q18: 4 | R18: =O18*P18*Q18 -> 20000 | T18: Y | U18: N | V18: N | W18: Direct Payment | AR18: =SUM(AS18:BD18) -> 20000 | AU18: 5000 | AX18: 5000 | BA18: 5000 | BD18: 5000 | BE18: =SUM(BF18:BQ18) -> 20000 | BH18: 5000 | BK18: 5000 | BN18: 5000 | BQ18: 5000 | BR18: =SUM(BS18:BU18) -> 0 | BY18: =IF(ISBLANK(C18),0,1) -> 0 | BZ18: =IF(ISBLANK(D18),0,1) -> 0 | CA18: =IF(ISBLANK(F18),0,1) -> 0 | CB18: =IF(ISBLANK(G18),0,1) -> 0 | CC18: =IF(ISBLANK(N18),0,1) -> 1
C19: Pillar 5:Luntiang Paaralan Dagdag Kariktan | K19: =VLOOKUP(J19,links!B$2:C$24,2,FALSE) -> #N/A | BY19: =IF(ISBLANK(C19),0,1) -> 1 | BZ19: =IF(ISBLANK(D19),0,1) -> 0 | CA19: =IF(ISBLANK(F19),0,1) -> 0 | CB19: =IF(ISBLANK(G19),0,1) -> 0 | CC19: =IF(ISBLANK(N19),0,1) -> 0
D20: Implemented Luntiang Paaralan Dagdag Kariktan | E20: 2 | H20: No. of Luntiang Paaralan Dagdag Kariktan implemented | K20: =VLOOKUP(J20,links!B$2:C$24,2,FALSE) -> #N/A | X20: =SUM(Y20:AD20) -> 0 | AE20: =SUM(AF20:AQ20) -> 1 | AJ20: 1 | BY20: =IF(ISBLANK(C20),0,1) -> 0 | BZ20: =IF(ISBLANK(D20),0,1) -> 1 | CA20: =IF(ISBLANK(F20),0,1) -> 0 | CB20: =IF(ISBLANK(G20),0,1) -> 0 | CC20: =IF(ISBLANK(N20),0,1) -> 0
G21: Conduct school clean and green activity | H21: No. of school clean and green activity conducted | K21: =VLOOKUP(J21,links!B$2:C$24,2,FALSE) -> #N/A | R21: =R22 -> 25000 | X21: =SUM(Y21:AD21) -> 0 | AE21: =SUM(AF21:AQ21) -> 1 | AJ21: 1 | AR21: =AR22 -> 25000 | AS21: =AS22 -> 0 | AT21: =AT22 -> 0 | AU21: =AU22 -> 0 | AV21: =AV22 -> 0 | AW21: =AW22 -> 25000 | AX21: =AX22 -> 0 | AY21: =AY22 -> 0 | ... BQ21: =BQ22 -> 0 | BY21: =IF(ISBLANK(C21),0,1) -> 0 | BZ21: =IF(ISBLANK(D21),0,1) -> 0 | CA21: =IF(ISBLANK(F21),0,1) -> 0 | CB21: =IF(ISBLANK(G21),0,1) -> 1 | CC21: =IF(ISBLANK(N21),0,1) -> 0
I22: MOOE | J22: Supplies and Materials Expenses | K22: =VLOOKUP(J22,[1]links!B$2:C$24,2,FALSE) -> Supplies_and_Materials_Expenses | L22: Other Supplies and Materials Expenses | M22: =VLOOKUP(L22,[1]links!K$2:L$222,2,FALSE) -> 75 | N22: supplies for BUG | O22: 1 | P22: 25000 | Q22: 1 | R22: =O22*P22*Q22 -> 25000 | T22: N | U22: Y | V22: N | W22: Direct Payment | AR22: =SUM(AS22:BD22) -> 25000 | AW22: 25000 | BE22: =SUM(BF22:BQ22) -> 25000 | BJ22: 25000 | BR22: =SUM(BS22:BU22) -> 0 | BY22: =IF(ISBLANK(C22),0,1) -> 0 | BZ22: =IF(ISBLANK(D22),0,1) -> 0 | CA22: =IF(ISBLANK(F22),0,1) -> 0 | CB22: =IF(ISBLANK(G22),0,1) -> 0 | CC22: =IF(ISBLANK(N22),0,1) -> 1
C23: Pillar 5:Luntiang Kapaligiran sa Paaralan at Pantahanan para sa disiplinang pangkalusugan | K23: =VLOOKUP(J23,links!B$2:C$24,2,FALSE) -> #N/A | BY23: =IF(ISBLANK(C23),0,1) -> 1 | BZ23: =IF(ISBLANK(D23),0,1) -> 0 | CA23: =IF(ISBLANK(F23),0,1) -> 0 | CB23: =IF(ISBLANK(G23),0,1) -> 0 | CC23: =IF(ISBLANK(N23),0,1) -> 0
D24: Implemented Luntiang Kapaligiran sa Paaralan at Pantahanan para sa disiplinang pangkalusugan | E24: 3 | H24: No. of Luntiang Kapaligiran sa Paaralan at Pantahanan para sa disiplinang pangkalusugan implemented | K24: =VLOOKUP(J24,links!B$2:C$24,2,FALSE) -> #N/A | X24: =SUM(Y24:AD24) -> 0 | AE24: =SUM(AF24:AQ24) -> 1 | AJ24: 1 | BY24: =IF(ISBLANK(C24),0,1) -> 0 | BZ24: =IF(ISBLANK(D24),0,1) -> 1 | CA24: =IF(ISBLANK(F24),0,1) -> 0 | CB24: =IF(ISBLANK(G24),0,1) -> 0 | CC24: =IF(ISBLANK(N24),0,1) -> 0
G25: Conduct procurement of various supplies and materials for Gulayan sa Paaralan | H25: No. of procurement of various supplies and materials for Gulayan sa Paaralan conducted | K25: =VLOOKUP(J25,links!B$2:C$24,2,FALSE) -> #N/A | R25: =R26 -> 25000 | X25: =SUM(Y25:AD25) -> 0 | AE25: =SUM(AF25:AQ25) -> 1 | AJ25: 1 | AR25: =AR26 -> 25000 | AS25: =AS26 -> 0 | AT25: =AT26 -> 0 | AU25: =AU26 -> 0 | AV25: =AV26 -> 0 | AW25: =AW26 -> 25000 | AX25: =AX26 -> 0 | AY25: =AY26 -> 0 | ... BQ25: =BQ26 -> 0 | BY25: =IF(ISBLANK(C25),0,1) -> 0 | BZ25: =IF(ISBLANK(D25),0,1) -> 0 | CA25: =IF(ISBLANK(F25),0,1) -> 0 | CB25: =IF(ISBLANK(G25),0,1) -> 1 | CC25: =IF(ISBLANK(N25),0,1) -> 0
I26: MOOE | J26: Supplies and Materials Expenses | K26: =VLOOKUP(J26,[1]links!B$2:C$24,2,FALSE) -> Supplies_and_Materials_Expenses | L26: Other Supplies and Materials Expenses | M26: =VLOOKUP(L26,[1]links!K$2:L$222,2,FALSE) -> 75 | N26: cleaning supplies and construction material | O26: 1 | P26: 25000 | Q26: 1 | R26: =O26*P26*Q26 -> 25000 | T26: N | U26: Y | V26: N | W26: Direct Payment | AR26: =SUM(AS26:BD26) -> 25000 | AW26: 25000 | BE26: =SUM(BF26:BQ26) -> 25000 | BJ26: 25000 | BR26: =SUM(BS26:BU26) -> 0 | BY26: =IF(ISBLANK(C26),0,1) -> 0 | BZ26: =IF(ISBLANK(D26),0,1) -> 0 | CA26: =IF(ISBLANK(F26),0,1) -> 0 | CB26: =IF(ISBLANK(G26),0,1) -> 0 | CC26: =IF(ISBLANK(N26),0,1) -> 1
C27: Pillar 4:Records Management Strand 2.1 | K27: =VLOOKUP(J27,links!B$2:C$24,2,FALSE) -> #N/A | BY27: =IF(ISBLANK(C27),0,1) -> 1 | BZ27: =IF(ISBLANK(D27),0,1) -> 0 | CA27: =IF(ISBLANK(F27),0,1) -> 0 | CB27: =IF(ISBLANK(G27),0,1) -> 0 | CC27: =IF(ISBLANK(N27),0,1) -> 0
D28: Distributed school identification card | E28: 4 | H28: No. of school identification card distributed | K28: =VLOOKUP(J28,links!B$2:C$24,2,FALSE) -> #N/A | X28: =SUM(Y28:AD28) -> 0 | AE28: =SUM(AF28:AQ28) -> 1 | AJ28: 1 | BY28: =IF(ISBLANK(C28),0,1) -> 0 | BZ28: =IF(ISBLANK(D28),0,1) -> 1 | CA28: =IF(ISBLANK(F28),0,1) -> 0 | CB28: =IF(ISBLANK(G28),0,1) -> 0 | CC28: =IF(ISBLANK(N28),0,1) -> 0
G29: Conduct procurement of supplies for school identification card for students | H29: No. of procurement of supplies for school identification card for students conducted | K29: =VLOOKUP(J29,links!B$2:C$24,2,FALSE) -> #N/A | R29: =R30 -> 3000 | X29: =SUM(Y29:AD29) -> 0 | AE29: =SUM(AF29:AQ29) -> 1 | AJ29: 1 | AR29: =AR30 -> 3000 | AS29: =AS30 -> 0 | AT29: =AT30 -> 0 | AU29: =AU30 -> 0 | AV29: =AV30 -> 0 | AW29: =AW30 -> 3000 | AX29: =AX30 -> 0 | AY29: =AY30 -> 0 | ... BQ29: =BQ30 -> 0 | BY29: =IF(ISBLANK(C29),0,1) -> 0 | BZ29: =IF(ISBLANK(D29),0,1) -> 0 | CA29: =IF(ISBLANK(F29),0,1) -> 0 | CB29: =IF(ISBLANK(G29),0,1) -> 1 | CC29: =IF(ISBLANK(N29),0,1) -> 0
I30: MOOE | J30: Supplies and Materials Expenses | K30: =VLOOKUP(J30,[1]links!B$2:C$24,2,FALSE) -> Supplies_and_Materials_Expenses | L30: Other Supplies and Materials Expenses | M30: =VLOOKUP(L30,[1]links!K$2:L$222,2,FALSE) -> 75 | N30: pvc card sheet | O30: 1 | P30: 3000 | Q30: 1 | R30: =O30*P30*Q30 -> 3000 | T30: N | U30: Y | V30: N | W30: Direct Payment | AR30: =SUM(AS30:BD30) -> 3000 | AW30: 3000 | BE30: =SUM(BF30:BQ30) -> 3000 | BJ30: 3000 | BR30: =SUM(BS30:BU30) -> 0 | BY30: =IF(ISBLANK(C30),0,1) -> 0 | BZ30: =IF(ISBLANK(D30),0,1) -> 0 | CA30: =IF(ISBLANK(F30),0,1) -> 0 | CB30: =IF(ISBLANK(G30),0,1) -> 0 | CC30: =IF(ISBLANK(N30),0,1) -> 1
C31: Pillar 5:SDRRMO TEA - (Tools and Equipment Acquisition Program) | K31: =VLOOKUP(J31,links!B$2:C$24,2,FALSE) -> #N/A | BY31: =IF(ISBLANK(C31),0,1) -> 1 | BZ31: =IF(ISBLANK(D31),0,1) -> 0 | CA31: =IF(ISBLANK(F31),0,1) -> 0 | CB31: =IF(ISBLANK(G31),0,1) -> 0 | CC31: =IF(ISBLANK(N31),0,1) -> 0
D32: Equipped School Disaster Risk and Reduction Management Program | E32: 5 | H32: No. of School Disaster Risk and Reduction Management Program equipped | K32: =VLOOKUP(J32,links!B$2:C$24,2,FALSE) -> #N/A | X32: =SUM(Y32:AD32) -> 0 | AE32: =SUM(AF32:AQ32) -> 1 | AJ32: 1 | BY32: =IF(ISBLANK(C32),0,1) -> 0 | BZ32: =IF(ISBLANK(D32),0,1) -> 1 | CA32: =IF(ISBLANK(F32),0,1) -> 0 | CB32: =IF(ISBLANK(G32),0,1) -> 0 | CC32: =IF(ISBLANK(N32),0,1) -> 0
G33: Procure chainsaw | H33: No. of chainsaw procured | K33: =VLOOKUP(J33,links!B$2:C$24,2,FALSE) -> #N/A | R33: =R34 -> 20000 | X33: =SUM(Y33:AD33) -> 0 | AE33: =SUM(AF33:AQ33) -> 1 | AJ33: 1 | AR33: =AR34 -> 20000 | AS33: =AS34 -> 0 | AT33: =AT34 -> 20000 | AU33: =AU34 -> 0 | AV33: =AV34 -> 0 | AW33: =AW34 -> 0 | AX33: =AX34 -> 0 | AY33: =AY34 -> 0 | ... BQ33: =BQ34 -> 0 | BY33: =IF(ISBLANK(C33),0,1) -> 0 | BZ33: =IF(ISBLANK(D33),0,1) -> 0 | CA33: =IF(ISBLANK(F33),0,1) -> 0 | CB33: =IF(ISBLANK(G33),0,1) -> 1 | CC33: =IF(ISBLANK(N33),0,1) -> 0
I34: MOOE | J34: Supplies and Materials Expenses | K34: =VLOOKUP(J34,[1]links!B$2:C$24,2,FALSE) -> Supplies_and_Materials_Expenses | L34: Disaster Response and Rescue Equipment | M34: =VLOOKUP(L34,[1]links!K$2:L$222,2,FALSE) -> 66 | N34: chainsaw | O34: 1 | P34: 20000 | Q34: 1 | R34: =O34*P34*Q34 -> 20000 | T34: N | U34: Y | V34: N | W34: Direct Payment | AR34: =SUM(AS34:BD34) -> 20000 | AT34: 20000 | BE34: =SUM(BF34:BQ34) -> 20000 | BG34: 20000 | BR34: =SUM(BS34:BU34) -> 0 | BY34: =IF(ISBLANK(C34),0,1) -> 0 | BZ34: =IF(ISBLANK(D34),0,1) -> 0 | CA34: =IF(ISBLANK(F34),0,1) -> 0 | CB34: =IF(ISBLANK(G34),0,1) -> 0 | CC34: =IF(ISBLANK(N34),0,1) -> 1
C35: Pillar1:PLACE - Provisin for Learners and Curriculum Enhancers | K35: =VLOOKUP(J35,links!B$2:C$24,2,FALSE) -> #N/A | BY35: =IF(ISBLANK(C35),0,1) -> 1 | BZ35: =IF(ISBLANK(D35),0,1) -> 0 | CA35: =IF(ISBLANK(F35),0,1) -> 0 | CB35: =IF(ISBLANK(G35),0,1) -> 0 | CC35: =IF(ISBLANK(N35),0,1) -> 0
D36: Provided classrooms with thermometer hygrometer | E36: 6 | H36: No. of classrooms with thermometer hygrometer provided | K36: =VLOOKUP(J36,links!B$2:C$24,2,FALSE) -> #N/A | X36: =SUM(Y36:AD36) -> 0 | AE36: =SUM(AF36:AQ36) -> 60 | AG36: 60 | BY36: =IF(ISBLANK(C36),0,1) -> 0 | BZ36: =IF(ISBLANK(D36),0,1) -> 1 | CA36: =IF(ISBLANK(F36),0,1) -> 0 | CB36: =IF(ISBLANK(G36),0,1) -> 0 | CC36: =IF(ISBLANK(N36),0,1) -> 0
G37: Procure thermometer hygrometer | H37: No. of thermometer hygrometer procured | K37: =VLOOKUP(J37,links!B$2:C$24,2,FALSE) -> #N/A | R37: =R38 -> 60000 | X37: =SUM(Y37:AD37) -> 0 | AE37: =SUM(AF37:AQ37) -> 60 | AG37: 60 | AR37: =AR38 -> 60000 | AS37: =AS38 -> 0 | AT37: =AT38 -> 60000 | AU37: =AU38 -> 0 | AV37: =AV38 -> 0 | AW37: =AW38 -> 0 | AX37: =AX38 -> 0 | AY37: =AY38 -> 0 | ... BQ37: =BQ38 -> 0 | BR37: =SUM(BR113:BR115) -> 0 | BS37: =SUM(BS113:BS115) -> 0 | BT37: =SUM(BT113:BT115) -> 0 | BU37: =SUM(BU113:BU115) -> 0 | BY37: =IF(ISBLANK(C37),0,1) -> 0 | BZ37: =IF(ISBLANK(D37),0,1) -> 0 | CA37: =IF(ISBLANK(F37),0,1) -> 0 | CB37: =IF(ISBLANK(G37),0,1) -> 1 | CC37: =IF(ISBLANK(N37),0,1) -> 0
I38: MOOE | J38: Supplies and Materials Expenses | K38: =VLOOKUP(J38,[1]links!B$2:C$24,2,FALSE) -> Supplies_and_Materials_Expenses | L38: Information and Communications Technology Equipment | M38: =VLOOKUP(L38,[1]links!K$2:L$222,2,FALSE) -> 62 | N38: thermometer hygrometer | O38: 60 | P38: 1000 | Q38: 1 | R38: =O38*P38*Q38 -> 60000 | T38: N | U38: Y | V38: N | W38: Direct Payment | AR38: =SUM(AS38:BD38) -> 60000 | AT38: 60000 | BE38: =SUM(BF38:BQ38) -> 60000 | BG38: 60000 | BR38: =SUM(BS38:BU38) -> 0 | BY38: =IF(ISBLANK(C38),0,1) -> 0 | BZ38: =IF(ISBLANK(D38),0,1) -> 0 | CA38: =IF(ISBLANK(F38),0,1) -> 0 | CB38: =IF(ISBLANK(G38),0,1) -> 0 | CC38: =IF(ISBLANK(N38),0,1) -> 1
C39: Pillar 1:Sports Enhancement Program | K39: =VLOOKUP(J39,links!B$2:C$24,2,FALSE) -> #N/A | BY39: =IF(ISBLANK(C39),0,1) -> 1 | BZ39: =IF(ISBLANK(D39),0,1) -> 0 | CA39: =IF(ISBLANK(F39),0,1) -> 0 | CB39: =IF(ISBLANK(G39),0,1) -> 0 | CC39: =IF(ISBLANK(N39),0,1) -> 0
D40: Equipped schools' individual, dual, and team sports | E40: 7 | H40: No. of schools' individual, dual, and team sports equipped | K40: =VLOOKUP(J40,links!B$2:C$24,2,FALSE) -> #N/A | X40: =SUM(Y40:AD40) -> 0 | AE40: =SUM(AF40:AQ40) -> 5 | AG40: 5 | BY40: =IF(ISBLANK(C40),0,1) -> 0 | BZ40: =IF(ISBLANK(D40),0,1) -> 1 | CA40: =IF(ISBLANK(F40),0,1) -> 0 | CB40: =IF(ISBLANK(G40),0,1) -> 0 | CC40: =IF(ISBLANK(N40),0,1) -> 0
G41: Conduct procurement of various sports equipment for Arnis, Badminton, 3x3 Baskketball, Futsal and Badminton | H41: No. of procurement of various sports equipment for Arnis, Badminton, 3x3 Baskketball, Futsal and Badminton conducted | K41: =VLOOKUP(J41,links!B$2:C$24,2,FALSE) -> #N/A | R41: =R42 -> 50000 | X41: =SUM(Y41:AD41) -> 0 | AE41: =SUM(AF41:AQ41) -> 1 | AG41: 1 | AR41: =AR42 -> 50000 | AS41: =AS42 -> 0 | AT41: =AT42 -> 50000 | AU41: =AU42 -> 0 | AV41: =AV42 -> 0 | AW41: =AW42 -> 0 | AX41: =AX42 -> 0 | AY41: =AY42 -> 0 | ... BQ41: =BQ42 -> 0 | BR41: =SUM(BR113:BR118) -> 3000 | BS41: =SUM(BS113:BS118) -> 0 | BT41: =SUM(BT113:BT118) -> 0 | BU41: =SUM(BU113:BU118) -> 0 | BY41: =IF(ISBLANK(C41),0,1) -> 0 | BZ41: =IF(ISBLANK(D41),0,1) -> 0 | CA41: =IF(ISBLANK(F41),0,1) -> 0 | CB41: =IF(ISBLANK(G41),0,1) -> 1 | CC41: =IF(ISBLANK(N41),0,1) -> 0
I42: MOOE | J42: Supplies and Materials Expenses | K42: =VLOOKUP(J42,[1]links!B$2:C$24,2,FALSE) -> Supplies_and_Materials_Expenses | L42: Sports Equipment | M42: =VLOOKUP(L42,[1]links!K$2:L$222,2,FALSE) -> 69 | N42: various sports equipment | O42: 1 | P42: 50000 | Q42: 1 | R42: =O42*P42*Q42 -> 50000 | T42: N | U42: Y | V42: N | W42: Direct Payment | AR42: =SUM(AS42:BD42) -> 50000 | AT42: 50000 | BE42: =SUM(BF42:BQ42) -> 50000 | BG42: 50000 | BR42: =SUM(BS42:BU42) -> 0 | BY42: =IF(ISBLANK(C42),0,1) -> 0 | BZ42: =IF(ISBLANK(D42),0,1) -> 0 | CA42: =IF(ISBLANK(F42),0,1) -> 0 | CB42: =IF(ISBLANK(G42),0,1) -> 0 | CC42: =IF(ISBLANK(N42),0,1) -> 1
D43: Equipped schools' special program for the arts | E43: 8 | H43: No. of schools' special program for the arts equipped | K43: =VLOOKUP(J43,links!B$2:C$24,2,FALSE) -> #N/A | X43: =SUM(Y43:AD43) -> 0 | AE43: =SUM(AF43:AQ43) -> 1 | AG43: 1 | BY43: =IF(ISBLANK(C43),0,1) -> 0 | BZ43: =IF(ISBLANK(D43),0,1) -> 1 | CA43: =IF(ISBLANK(F43),0,1) -> 0 | CB43: =IF(ISBLANK(G43),0,1) -> 0 | CC43: =IF(ISBLANK(N43),0,1) -> 0
G44: Procure airconditioning unit | H44: No. of airconditioning unit procured | K44: =VLOOKUP(J44,links!B$2:C$24,2,FALSE) -> #N/A | R44: =R45 -> 35000 | X44: =SUM(Y44:AD44) -> 0 | AE44: =SUM(AF44:AQ44) -> 1 | AG44: 1 | AR44: =AR45 -> 35000 | AS44: =AS45 -> 0 | AT44: =AT45 -> 35000 | AU44: =AU45 -> 0 | AV44: =AV45 -> 0 | AW44: =AW45 -> 0 | AX44: =AX45 -> 0 | AY44: =AY45 -> 0 | ... BQ44: =BQ45 -> 0 | BR44: =SUM(BR113:BR122) -> 3000 | BS44: =SUM(BS113:BS122) -> 0 | BT44: =SUM(BT113:BT122) -> 0 | BU44: =SUM(BU113:BU122) -> 0 | BY44: =IF(ISBLANK(C44),0,1) -> 0 | BZ44: =IF(ISBLANK(D44),0,1) -> 0 | CA44: =IF(ISBLANK(F44),0,1) -> 0 | CB44: =IF(ISBLANK(G44),0,1) -> 1 | CC44: =IF(ISBLANK(N44),0,1) -> 0
I45: MOOE | J45: Supplies and Materials Expenses | K45: =VLOOKUP(J45,[1]links!B$2:C$24,2,FALSE) -> Supplies_and_Materials_Expenses | L45: Office Equipment | M45: =VLOOKUP(L45,[1]links!K$2:L$222,2,FALSE) -> 61 | N45: airconditioning unit | O45: 1 | P45: 35000 | Q45: 1 | R45: =O45*P45*Q45 -> 35000 | T45: N | U45: Y | V45: N | W45: Direct Payment | AR45: =SUM(AS45:BD45) -> 35000 | AT45: 35000 | BE45: =SUM(BF45:BQ45) -> 35000 | BG45: 35000 | BR45: =SUM(BS45:BU45) -> 0 | BY45: =IF(ISBLANK(C45),0,1) -> 0 | BZ45: =IF(ISBLANK(D45),0,1) -> 0 | CA45: =IF(ISBLANK(F45),0,1) -> 0 | CB45: =IF(ISBLANK(G45),0,1) -> 0 | CC45: =IF(ISBLANK(N45),0,1) -> 1
C46: Pillar 1:It's More Fun in Aral Pan | K46: =VLOOKUP(J46,links!B$2:C$24,2,FALSE) -> #N/A | BY46: =IF(ISBLANK(C46),0,1) -> 1 | BZ46: =IF(ISBLANK(D46),0,1) -> 0 | CA46: =IF(ISBLANK(F46),0,1) -> 0 | CB46: =IF(ISBLANK(G46),0,1) -> 0 | CC46: =IF(ISBLANK(N46),0,1) -> 0
D47: Provided repository of students' outputs | E47: 9 | H47: No. of repository of students' outputs provided | K47: =VLOOKUP(J47,links!B$2:C$24,2,FALSE) -> #N/A | X47: =SUM(Y47:AD47) -> 0 | AE47: =SUM(AF47:AQ47) -> 2 | AJ47: 2 | BY47: =IF(ISBLANK(C47),0,1) -> 0 | BZ47: =IF(ISBLANK(D47),0,1) -> 1 | CA47: =IF(ISBLANK(F47),0,1) -> 0 | CB47: =IF(ISBLANK(G47),0,1) -> 0 | CC47: =IF(ISBLANK(N47),0,1) -> 0
G48: Procure cabinets for safekeeping of students' output | H48: No. of cabinets for safekeeping of students' output procured | K48: =VLOOKUP(J48,links!B$2:C$24,2,FALSE) -> #N/A | R48: =R49 -> 25000 | X48: =SUM(Y48:AD48) -> 0 | AE48: =SUM(AF48:AQ48) -> 2 | AJ48: 2 | AR48: =AR49 -> 25000 | AS48: =AS49 -> 0 | AT48: =AT49 -> 0 | AU48: =AU49 -> 0 | AV48: =AV49 -> 0 | AW48: =AW49 -> 25000 | AX48: =AX49 -> 0 | AY48: =AY49 -> 0 | ... BQ48: =BQ49 -> 0 | BR48: =SUM(BR113:BR126) -> 3000 | BS48: =SUM(BS113:BS126) -> 0 | BT48: =SUM(BT113:BT126) -> 0 | BU48: =SUM(BU113:BU126) -> 0 | BY48: =IF(ISBLANK(C48),0,1) -> 0 | BZ48: =IF(ISBLANK(D48),0,1) -> 0 | CA48: =IF(ISBLANK(F48),0,1) -> 0 | CB48: =IF(ISBLANK(G48),0,1) -> 1 | CC48: =IF(ISBLANK(N48),0,1) -> 0
I49: MOOE | J49: Supplies and Materials Expenses | K49: =VLOOKUP(J49,[1]links!B$2:C$24,2,FALSE) -> Supplies_and_Materials_Expenses | L49: Furniture and Fixtures | M49: =VLOOKUP(L49,[1]links!K$2:L$222,2,FALSE) -> 73 | N49: cabinets | O49: 2 | P49: 12500 | Q49: 1 | R49: =O49*P49*Q49 -> 25000 | T49: N | U49: Y | V49: N | W49: Direct Payment | AR49: =SUM(AS49:BD49) -> 25000 | AW49: 25000 | BE49: =SUM(BF49:BQ49) -> 25000 | BJ49: 25000 | BR49: =SUM(BS49:BU49) -> 0 | BY49: =IF(ISBLANK(C49),0,1) -> 0 | BZ49: =IF(ISBLANK(D49),0,1) -> 0 | CA49: =IF(ISBLANK(F49),0,1) -> 0 | CB49: =IF(ISBLANK(G49),0,1) -> 0 | CC49: =IF(ISBLANK(N49),0,1) -> 1
C50: Pillar 1:Project A Scien-Ment - Accessibility of Science Materials Enhancement in the New Normal Teaching | K50: =VLOOKUP(J50,links!B$2:C$24,2,FALSE) -> #N/A | BY50: =IF(ISBLANK(C50),0,1) -> 1 | BZ50: =IF(ISBLANK(D50),0,1) -> 0 | CA50: =IF(ISBLANK(F50),0,1) -> 0 | CB50: =IF(ISBLANK(G50),0,1) -> 0 | CC50: =IF(ISBLANK(N50),0,1) -> 0
D51: Developed a fully functional science laboratory with research and experimental apparatus | E51: 10 | H51: No. of a fully functional science laboratory with research and experimental apparatus developed | K51: =VLOOKUP(J51,links!B$2:C$24,2,FALSE) -> #N/A | X51: =SUM(Y51:AD51) -> 0 | AE51: =SUM(AF51:AQ51) -> 1 | AJ51: 1 | BY51: =IF(ISBLANK(C51),0,1) -> 0 | BZ51: =IF(ISBLANK(D51),0,1) -> 1 | CA51: =IF(ISBLANK(F51),0,1) -> 0 | CB51: =IF(ISBLANK(G51),0,1) -> 0 | CC51: =IF(ISBLANK(N51),0,1) -> 0
G52: Conduct procurement of scietific equipment for researches and experimentations | H52: No. of procurement of scietific equipment for researches and experimentations conducted | K52: =VLOOKUP(J52,links!B$2:C$24,2,FALSE) -> #N/A | R52: =R53 -> 55000 | X52: =SUM(Y52:AD52) -> 0 | AE52: =SUM(AF52:AQ52) -> 1 | AJ52: 1 | AR52: =AR53 -> 55000 | AS52: =AS53 -> 0 | AT52: =AT53 -> 0 | AU52: =AU53 -> 0 | AV52: =AV53 -> 0 | AW52: =AW53 -> 55000 | AX52: =AX53 -> 0 | AY52: =AY53 -> 0 | ... BQ52: =BQ53 -> 0 | BR52: =SUM(BR117:BR140) -> 6000 | BS52: =SUM(BS117:BS140) -> 0 | BT52: =SUM(BT117:BT140) -> 0 | BU52: =SUM(BU117:BU140) -> 0 | BY52: =IF(ISBLANK(C52),0,1) -> 0 | BZ52: =IF(ISBLANK(D52),0,1) -> 0 | CA52: =IF(ISBLANK(F52),0,1) -> 0 | CB52: =IF(ISBLANK(G52),0,1) -> 1 | CC52: =IF(ISBLANK(N52),0,1) -> 0
I53: MOOE | J53: Supplies and Materials Expenses | K53: =VLOOKUP(J53,[1]links!B$2:C$24,2,FALSE) -> Supplies_and_Materials_Expenses | L53: Technical and Scientific Equipment | M53: =VLOOKUP(L53,[1]links!K$2:L$222,2,FALSE) -> 70 | N53: scientific equipment | O53: 1 | P53: 55000 | Q53: 1 | R53: =O53*P53*Q53 -> 55000 | T53: N | U53: Y | V53: N | W53: Direct Payment | AR53: =SUM(AS53:BD53) -> 55000 | AW53: 55000 | BE53: =SUM(BF53:BQ53) -> 55000 | BJ53: 55000 | BR53: =SUM(BS53:BU53) -> 0 | BY53: =IF(ISBLANK(C53),0,1) -> 0 | BZ53: =IF(ISBLANK(D53),0,1) -> 0 | CA53: =IF(ISBLANK(F53),0,1) -> 0 | CB53: =IF(ISBLANK(G53),0,1) -> 0 | CC53: =IF(ISBLANK(N53),0,1) -> 1
C54: Pillar 3:RATSADA AGILA | K54: =VLOOKUP(J54,links!B$2:C$24,2,FALSE) -> #N/A | BY54: =IF(ISBLANK(C54),0,1) -> 1 | BZ54: =IF(ISBLANK(D54),0,1) -> 0 | CA54: =IF(ISBLANK(F54),0,1) -> 0 | CB54: =IF(ISBLANK(G54),0,1) -> 0 | CC54: =IF(ISBLANK(N54),0,1) -> 0
D55: Improved implementation of school literacy program | E55: 11 | H55: No of implementation of school literacy program improved | K55: =VLOOKUP(J55,links!B$2:C$24,2,FALSE) -> #N/A | X55: =SUM(Y55:AD55) -> 0 | AE55: =SUM(AF55:AQ55) -> 1 | AJ55: 1 | BY55: =IF(ISBLANK(C55),0,1) -> 0 | BZ55: =IF(ISBLANK(D55),0,1) -> 1 | CA55: =IF(ISBLANK(F55),0,1) -> 0 | CB55: =IF(ISBLANK(G55),0,1) -> 0 | CC55: =IF(ISBLANK(N55),0,1) -> 0
G56: Conduct procurement of office supplies | H56: No. procurement of office supplies conducted | K56: =VLOOKUP(J56,links!B$2:C$24,2,FALSE) -> #N/A | R56: =R57 -> 5000 | X56: =SUM(Y56:AD56) -> 0 | AE56: =SUM(AF56:AQ56) -> 1 | AJ56: 1 | AR56: =AR57 -> 5000 | AS56: =AS57 -> 0 | AT56: =AT57 -> 0 | AU56: =AU57 -> 0 | AV56: =AV57 -> 0 | AW56: =AW57 -> 5000 | AX56: =AX57 -> 0 | AY56: =AY57 -> 0 | ... BQ56: =BQ57 -> 0 | BR56: =SUM(BR121:BR144) -> 3000 | BS56: =SUM(BS121:BS144) -> 0 | BT56: =SUM(BT121:BT144) -> 0 | BU56: =SUM(BU121:BU144) -> 0 | BY56: =IF(ISBLANK(C56),0,1) -> 0 | BZ56: =IF(ISBLANK(D56),0,1) -> 0 | CA56: =IF(ISBLANK(F56),0,1) -> 0 | CB56: =IF(ISBLANK(G56),0,1) -> 1 | CC56: =IF(ISBLANK(N56),0,1) -> 0
I57: MOOE | J57: Supplies and Materials Expenses | K57: =VLOOKUP(J57,[1]links!B$2:C$24,2,FALSE) -> Supplies_and_Materials_Expenses | L57: Office Supplies Expenses | M57: =VLOOKUP(L57,[1]links!K$2:L$222,2,FALSE) -> 47 | N57: office supplies | O57: 1 | P57: 5000 | Q57: 1 | R57: =O57*P57*Q57 -> 5000 | T57: N | U57: Y | V57: N | W57: Direct Payment | AR57: =SUM(AS57:BD57) -> 5000 | AW57: 5000 | BE57: =SUM(BF57:BQ57) -> 5000 | BJ57: 5000 | BR57: =SUM(BS57:BU57) -> 0 | BY57: =IF(ISBLANK(C57),0,1) -> 0 | BZ57: =IF(ISBLANK(D57),0,1) -> 0 | CA57: =IF(ISBLANK(F57),0,1) -> 0 | CB57: =IF(ISBLANK(G57),0,1) -> 0 | CC57: =IF(ISBLANK(N57),0,1) -> 1
G58: Procure airconditioning unit for literacy center | H58: No. of airconditioning unit for literacy center procured | K58: =VLOOKUP(J58,links!B$2:C$24,2,FALSE) -> #N/A | R58: =R59 -> 30000 | X58: =SUM(Y58:AD58) -> 0 | AE58: =SUM(AF58:AQ58) -> 2 | AJ58: 1 | AO58: 1 | AR58: =AR59 -> 30000 | AS58: =AS59 -> 0 | AT58: =AT59 -> 0 | AU58: =AU59 -> 0 | AV58: =AV59 -> 0 | AW58: =AW59 -> 30000 | AX58: =AX59 -> 0 | AY58: =AY59 -> 0 | ... BQ58: =BQ59 -> 0 | BR58: =SUM(BR123:BR146) -> 3000 | BS58: =SUM(BS123:BS146) -> 0 | BT58: =SUM(BT123:BT146) -> 0 | BU58: =SUM(BU123:BU146) -> 0 | BY58: =IF(ISBLANK(C58),0,1) -> 0 | BZ58: =IF(ISBLANK(D58),0,1) -> 0 | CA58: =IF(ISBLANK(F58),0,1) -> 0 | CB58: =IF(ISBLANK(G58),0,1) -> 1 | CC58: =IF(ISBLANK(N58),0,1) -> 0
I59: MOOE | J59: Supplies and Materials Expenses | K59: =VLOOKUP(J59,[1]links!B$2:C$24,2,FALSE) -> Supplies_and_Materials_Expenses | L59: Office Equipment | M59: =VLOOKUP(L59,[1]links!K$2:L$222,2,FALSE) -> 61 | N59: airconditioning unit | O59: 1 | P59: 30000 | Q59: 1 | R59: =O59*P59*Q59 -> 30000 | T59: N | U59: Y | V59: N | W59: Direct Payment | AR59: =SUM(AS59:BD59) -> 30000 | AW59: 30000 | BE59: =SUM(BF59:BQ59) -> 30000 | BJ59: 30000 | BR59: =SUM(BS59:BU59) -> 0 | BY59: =IF(ISBLANK(C59),0,1) -> 0 | BZ59: =IF(ISBLANK(D59),0,1) -> 0 | CA59: =IF(ISBLANK(F59),0,1) -> 0 | CB59: =IF(ISBLANK(G59),0,1) -> 0 | CC59: =IF(ISBLANK(N59),0,1) -> 1
G60: Repair Filipino faculty office | H60: No. of Filipino faculty office repaired | K60: =VLOOKUP(J60,links!B$2:C$24,2,FALSE) -> #N/A | R60: =R61 -> 50000 | X60: =SUM(Y60:AD60) -> 0 | AE60: =SUM(AF60:AQ60) -> 2 | AJ60: 1 | AO60: 1 | AR60: =AR61 -> 50000 | AS60: =AS61 -> 0 | AT60: =AT61 -> 0 | AU60: =AU61 -> 0 | AV60: =AV61 -> 0 | AW60: =AW61 -> 0 | AX60: =AX61 -> 0 | AY60: =AY61 -> 0 | ... BQ60: =BQ61 -> 0 | BR60: =SUM(BR125:BR148) -> 3000 | BS60: =SUM(BS125:BS148) -> 0 | BT60: =SUM(BT125:BT148) -> 0 | BU60: =SUM(BU125:BU148) -> 0 | BY60: =IF(ISBLANK(C60),0,1) -> 0 | BZ60: =IF(ISBLANK(D60),0,1) -> 0 | CA60: =IF(ISBLANK(F60),0,1) -> 0 | CB60: =IF(ISBLANK(G60),0,1) -> 1 | CC60: =IF(ISBLANK(N60),0,1) -> 0
I61: MOOE | J61: Repairs and Maintenance | K61: =VLOOKUP(J61,[1]links!B$2:C$24,2,FALSE) -> Repairs_and_Maintenance | L61: Other Structures | M61: =VLOOKUP(L61,[1]links!K$2:L$222,2,FALSE) -> 114 | N61: labor and materials | O61: 1 | P61: 50000 | Q61: 1 | R61: =O61*P61*Q61 -> 50000 | T61: Y | U61: N | V61: N | W61: Direct Payment | AR61: =SUM(AS61:BD61) -> 50000 | BB61: 50000 | BE61: =SUM(BF61:BQ61) -> 50000 | BO61: 50000 | BR61: =SUM(BS61:BU61) -> 0 | BY61: =IF(ISBLANK(C61),0,1) -> 0 | BZ61: =IF(ISBLANK(D61),0,1) -> 0 | CA61: =IF(ISBLANK(F61),0,1) -> 0 | CB61: =IF(ISBLANK(G61),0,1) -> 0 | CC61: =IF(ISBLANK(N61),0,1) -> 1
C62: Pillar 3:Eagle in Motion | K62: =VLOOKUP(J62,links!B$2:C$24,2,FALSE) -> #N/A | BY62: =IF(ISBLANK(C62),0,1) -> 1 | BZ62: =IF(ISBLANK(D62),0,1) -> 0 | CA62: =IF(ISBLANK(F62),0,1) -> 0 | CB62: =IF(ISBLANK(G62),0,1) -> 0 | CC62: =IF(ISBLANK(N62),0,1) -> 0
D63: Improved implementation of school numeracy program | E63: 12 | H63: No of implementation of school numeracy program improved | K63: =VLOOKUP(J63,links!B$2:C$24,2,FALSE) -> #N/A | X63: =SUM(Y63:AD63) -> 0 | AE63: =SUM(AF63:AQ63) -> 1 | AM63: 1 | BY63: =IF(ISBLANK(C63),0,1) -> 0 | BZ63: =IF(ISBLANK(D63),0,1) -> 1 | CA63: =IF(ISBLANK(F63),0,1) -> 0 | CB63: =IF(ISBLANK(G63),0,1) -> 0 | CC63: =IF(ISBLANK(N63),0,1) -> 0
G64: Conduct repair of numeracy center | H64: No. of repair of numeracy center conducted | K64: =VLOOKUP(J64,links!B$2:C$24,2,FALSE) -> #N/A | R64: =R65 -> 50000 | X64: =SUM(Y64:AD64) -> 0 | AE64: =SUM(AF64:AQ64) -> 1 | AM64: 1 | AR64: =AR65 -> 50000 | AS64: =AS65 -> 0 | AT64: =AT65 -> 0 | AU64: =AU65 -> 0 | AV64: =AV65 -> 0 | AW64: =AW65 -> 0 | AX64: =AX65 -> 0 | AY64: =AY65 -> 0 | ... BQ64: =BQ65 -> 0 | BR64: =SUM(BR139:BR156) -> 0 | BS64: =SUM(BS139:BS156) -> 0 | BT64: =SUM(BT139:BT156) -> 0 | BU64: =SUM(BU139:BU156) -> 0 | BY64: =IF(ISBLANK(C64),0,1) -> 0 | BZ64: =IF(ISBLANK(D64),0,1) -> 0 | CA64: =IF(ISBLANK(F64),0,1) -> 0 | CB64: =IF(ISBLANK(G64),0,1) -> 1 | CC64: =IF(ISBLANK(N64),0,1) -> 0
I65: MOOE | J65: Repairs and Maintenance | K65: =VLOOKUP(J65,[1]links!B$2:C$24,2,FALSE) -> Repairs_and_Maintenance | L65: Other Structures | M65: =VLOOKUP(L65,[1]links!K$2:L$222,2,FALSE) -> 114 | N65: labor and materials | O65: 1 | P65: 50000 | Q65: 1 | R65: =O65*P65*Q65 -> 50000 | T65: Y | U65: N | V65: N | W65: Direct Payment | AR65: =SUM(AS65:BD65) -> 50000 | AZ65: 50000 | BE65: =SUM(BF65:BQ65) -> 50000 | BM65: 50000 | BR65: =SUM(BS65:BU65) -> 0 | BY65: =IF(ISBLANK(C65),0,1) -> 0 | BZ65: =IF(ISBLANK(D65),0,1) -> 0 | CA65: =IF(ISBLANK(F65),0,1) -> 0 | CB65: =IF(ISBLANK(G65),0,1) -> 0 | CC65: =IF(ISBLANK(N65),0,1) -> 1
C66: Pillar 5:Learning and Development | K66: =VLOOKUP(J66,links!B$2:C$24,2,FALSE) -> #N/A | BY66: =IF(ISBLANK(C66),0,1) -> 1 | BZ66: =IF(ISBLANK(D66),0,1) -> 0 | CA66: =IF(ISBLANK(F66),0,1) -> 0 | CB66: =IF(ISBLANK(G66),0,1) -> 0 | CC66: =IF(ISBLANK(N66),0,1) -> 0
D67: Completed LAC Session | E67: 13 | H67: No. of LAC session completed | K67: =VLOOKUP(J67,links!B$2:C$24,2,FALSE) -> #N/A | X67: =SUM(Y67:AD67) -> 0 | AE67: =SUM(AF67:AQ67) -> 10 | AG67: 1 | AH67: 1 | AI67: 1 | AJ67: 1 | AK67: 1 | AL67: 1 | AM67: 1 | AN67: 1 | AO67: 1 | AP67: 1 | BY67: =IF(ISBLANK(C67),0,1) -> 0 | BZ67: =IF(ISBLANK(D67),0,1) -> 1 | CA67: =IF(ISBLANK(F67),0,1) -> 0 | CB67: =IF(ISBLANK(G67),0,1) -> 0 | CC67: =IF(ISBLANK(N67),0,1) -> 0
G68: Conduct School-based learning action cell | H68: No. od school based learning action cell conducted | K68: =VLOOKUP(J68,links!B$2:C$24,2,FALSE) -> #N/A | R68: =R69 -> 40000 | X68: =SUM(Y68:AD68) -> 0 | AE68: =SUM(AF68:AQ68) -> 10 | AG68: 1 | AH68: 1 | AI68: 1 | AJ68: 1 | AK68: 1 | AL68: 1 | AM68: 1 | AN68: 1 | AO68: 1 | AP68: 1 | AR68: =AR69 -> 40000 | AS68: =AS69 -> 0 | AT68: =AT69 -> 10000 | AU68: =AU69 -> 0 | AV68: =AV69 -> 10000 | AW68: =AW69 -> 0 | AX68: =AX69 -> 0 | AY68: =AY69 -> 0 | ... BQ68: =BQ69 -> 0 | BR68: =SUM(BR143:BR159) -> 0 | BS68: =SUM(BS143:BS159) -> 0 | BT68: =SUM(BT143:BT159) -> 0 | BU68: =SUM(BU143:BU159) -> 0 | BY68: =IF(ISBLANK(C68),0,1) -> 0 | BZ68: =IF(ISBLANK(D68),0,1) -> 0 | CA68: =IF(ISBLANK(F68),0,1) -> 0 | CB68: =IF(ISBLANK(G68),0,1) -> 1 | CC68: =IF(ISBLANK(N68),0,1) -> 0
I69: MOOE | J69: Training and Scholarship Expenses | K69: =VLOOKUP(J69,[1]links!B$2:C$24,2,FALSE) -> Training_and_Scholarship_Expenses | L69: Training Expenses | M69: =VLOOKUP(L69,[1]links!K$2:L$222,2,FALSE) -> 44 | N69: snacks during the conduct of LAC session | O69: 1 | P69: 10000 | Q69: 4 | R69: =O69*P69*Q69 -> 40000 | T69: Y | U69: N | V69: N | W69: Direct Payment | AR69: =SUM(AS69:BD69) -> 40000 | AT69: 10000 | AV69: 10000 | BA69: 10000 | BC69: 10000 | BE69: =SUM(BF69:BQ69) -> 40000 | BG69: 10000 | BI69: 10000 | BN69: 10000 | BP69: 10000 | BR69: =SUM(BS69:BU69) -> 0 | BY69: =IF(ISBLANK(C69),0,1) -> 0 | BZ69: =IF(ISBLANK(D69),0,1) -> 0 | CA69: =IF(ISBLANK(F69),0,1) -> 0 | CB69: =IF(ISBLANK(G69),0,1) -> 0 | CC69: =IF(ISBLANK(N69),0,1) -> 1
D70: Capacitated teaching personnel in the conduct of In-Service Training | E70: 14 | H70: No. of teaching personnel in the conduct of In-Service Training capacitated | K70: =VLOOKUP(J70,links!B$2:C$24,2,FALSE) -> #N/A | X70: =SUM(Y70:AD70) -> 0 | AE70: =SUM(AF70:AQ70) -> 100 | AO70: 100 | BY70: =IF(ISBLANK(C70),0,1) -> 0 | BZ70: =IF(ISBLANK(D70),0,1) -> 1 | CA70: =IF(ISBLANK(F70),0,1) -> 0 | CB70: =IF(ISBLANK(G70),0,1) -> 0 | CC70: =IF(ISBLANK(N70),0,1) -> 0
G71: Conduct In-Service Training for teaching personnel | H71: No. of In-Service Training for teaching personnel conducted | K71: =VLOOKUP(J71,links!B$2:C$24,2,FALSE) -> #N/A | R71: =R72 -> 140000 | X71: =SUM(Y71:AD71) -> 0 | AE71: =SUM(AF71:AQ71) -> 1 | AO71: 1 | AR71: =AR72 -> 140000 | AS71: =AS72 -> 0 | AT71: =AT72 -> 0 | AU71: =AU72 -> 0 | AV71: =AV72 -> 0 | AW71: =AW72 -> 0 | AX71: =AX72 -> 0 | AY71: =AY72 -> 0 | ... BQ71: =BQ72 -> 0 | BR71: =SUM(BR146:BR162) -> 0 | BS71: =SUM(BS146:BS162) -> 0 | BT71: =SUM(BT146:BT162) -> 0 | BU71: =SUM(BU146:BU162) -> 0 | BY71: =IF(ISBLANK(C71),0,1) -> 0 | BZ71: =IF(ISBLANK(D71),0,1) -> 0 | CA71: =IF(ISBLANK(F71),0,1) -> 0 | CB71: =IF(ISBLANK(G71),0,1) -> 1 | CC71: =IF(ISBLANK(N71),0,1) -> 0
I72: MOOE | J72: Training and Scholarship Expenses | K72: =VLOOKUP(J72,[1]links!B$2:C$24,2,FALSE) -> Training_and_Scholarship_Expenses | L72: Training Expenses | M72: =VLOOKUP(L72,[1]links!K$2:L$222,2,FALSE) -> 44 | N72: snacks during the conduct of INSET | O72: 1 | P72: 33000 | Q72: 5 | R72: 140000 | T72: Y | U72: N | V72: N | W72: Direct Payment | AR72: 140000 | BB72: 140000 | BE72: =SUM(BF72:BQ72) -> 140000 | BO72: 140000 | BR72: =SUM(BS72:BU72) -> 0 | BY72: =IF(ISBLANK(C72),0,1) -> 0 | BZ72: =IF(ISBLANK(D72),0,1) -> 0 | CA72: =IF(ISBLANK(F72),0,1) -> 0 | CB72: =IF(ISBLANK(G72),0,1) -> 0 | CC72: =IF(ISBLANK(N72),0,1) -> 1
C73: Pillar 5:GAWAD AGILA | K73: =VLOOKUP(J73,links!B$2:C$24,2,FALSE) -> #N/A | BY73: =IF(ISBLANK(C73),0,1) -> 1 | BZ73: =IF(ISBLANK(D73),0,1) -> 0 | CA73: =IF(ISBLANK(F73),0,1) -> 0 | CB73: =IF(ISBLANK(G73),0,1) -> 0 | CC73: =IF(ISBLANK(N73),0,1) -> 0
D74: Implemented Awards and Recognition | E74: 15 | H74: No. of Awards and Recognition implemented | K74: =VLOOKUP(J74,links!B$2:C$24,2,FALSE) -> #N/A | X74: =SUM(Y74:AD74) -> 0 | AE74: =SUM(AF74:AQ74) -> 1 | AN74: 1 | BY74: =IF(ISBLANK(C74),0,1) -> 0 | BZ74: =IF(ISBLANK(D74),0,1) -> 1 | CA74: =IF(ISBLANK(F74),0,1) -> 0 | CB74: =IF(ISBLANK(G74),0,1) -> 0 | CC74: =IF(ISBLANK(N74),0,1) -> 0
G75: Conduct school -based faculty and staff awards and recognition | H75: No. of school-based faculty and staff awards and recognition conducted | K75: =VLOOKUP(J75,links!B$2:C$24,2,FALSE) -> #N/A | R75: =R76 -> 90000 | X75: =SUM(Y75:AD75) -> 0 | AE75: =SUM(AF75:AQ75) -> 1 | AN75: 1 | AR75: =AR76 -> 90000 | AS75: =AS76 -> 0 | AT75: =AT76 -> 0 | AU75: =AU76 -> 0 | AV75: =AV76 -> 0 | AW75: =AW76 -> 0 | AX75: =AX76 -> 0 | AY75: =AY76 -> 0 | ... BQ75: =BQ76 -> 0 | BR75: =SUM(BR155:BR166) -> 0 | BS75: =SUM(BS155:BS166) -> 0 | BT75: =SUM(BT155:BT166) -> 0 | BU75: =SUM(BU155:BU166) -> 0 | BY75: =IF(ISBLANK(C75),0,1) -> 0 | BZ75: =IF(ISBLANK(D75),0,1) -> 0 | CA75: =IF(ISBLANK(F75),0,1) -> 0 | CB75: =IF(ISBLANK(G75),0,1) -> 1 | CC75: =IF(ISBLANK(N75),0,1) -> 0
I76: MOOE | J76: Training and Scholarship Expenses | K76: =VLOOKUP(J76,[1]links!B$2:C$24,2,FALSE) -> Training_and_Scholarship_Expenses | L76: Training Expenses | M76: =VLOOKUP(L76,[1]links!K$2:L$222,2,FALSE) -> 44 | N76: meal and venue | O76: 1 | P76: 90000 | Q76: 1 | R76: =O76*P76*Q76 -> 90000 | T76: Y | U76: N | V76: N | W76: Direct Payment | AR76: =SUM(AS76:BD76) -> 90000 | BA76: 90000 | BE76: =SUM(BF76:BQ76) -> 90000 | BN76: 90000 | BR76: =SUM(BS76:BU76) -> 0 | BY76: =IF(ISBLANK(C76),0,1) -> 0 | BZ76: =IF(ISBLANK(D76),0,1) -> 0 | CA76: =IF(ISBLANK(F76),0,1) -> 0 | CB76: =IF(ISBLANK(G76),0,1) -> 0 | CC76: =IF(ISBLANK(N76),0,1) -> 1
C77: Pillar 1:Pabonggahan ng Talento sa Teknolohiya | K77: =VLOOKUP(J77,links!B$2:C$24,2,FALSE) -> #N/A | BY77: =IF(ISBLANK(C77),0,1) -> 1 | BZ77: =IF(ISBLANK(D77),0,1) -> 0 | CA77: =IF(ISBLANK(F77),0,1) -> 0 | CB77: =IF(ISBLANK(G77),0,1) -> 0 | CC77: =IF(ISBLANK(N77),0,1) -> 0
D78: Equipped TLE offerings with tools and equipment | E78: 16 | H78: No. of TLE offering with tools and equipment equipped | K78: =VLOOKUP(J78,links!B$2:C$24,2,FALSE) -> #N/A | X78: =SUM(Y78:AD78) -> 0 | AE78: =SUM(AF78:AQ78) -> 5 | AG78: 5 | BY78: =IF(ISBLANK(C78),0,1) -> 0 | BZ78: =IF(ISBLANK(D78),0,1) -> 1 | CA78: =IF(ISBLANK(F78),0,1) -> 0 | CB78: =IF(ISBLANK(G78),0,1) -> 0 | CC78: =IF(ISBLANK(N78),0,1) -> 0
G79: Conduct procurement of sewing machine for needlecraft offering | H79: No. of procurement of sewing machine for needlecraft offering conducted | K79: =VLOOKUP(J79,links!B$2:C$24,2,FALSE) -> #N/A | R79: =R80 -> 5000 | X79: =SUM(Y79:AD79) -> 0 | AE79: =SUM(AF79:AQ79) -> 1 | AG79: 1 | AR79: =AR80 -> 5000 | AS79: =AS80 -> 0 | AT79: =AT80 -> 5000 | AU79: =AU80 -> 0 | AV79: =AV80 -> 0 | AW79: =AW80 -> 0 | AX79: =AX80 -> 0 | AY79: =AY80 -> 0 | ... BQ79: =BQ80 -> 0 | BR79: =SUM(BR157:BR170) -> 0 | BS79: =SUM(BS157:BS170) -> 0 | BT79: =SUM(BT157:BT170) -> 0 | BU79: =SUM(BU157:BU170) -> 0 | BY79: =IF(ISBLANK(C79),0,1) -> 0 | BZ79: =IF(ISBLANK(D79),0,1) -> 0 | CA79: =IF(ISBLANK(F79),0,1) -> 0 | CB79: =IF(ISBLANK(G79),0,1) -> 1 | CC79: =IF(ISBLANK(N79),0,1) -> 0
I80: MOOE | J80: Supplies and Materials Expenses | K80: =VLOOKUP(J80,[1]links!B$2:C$24,2,FALSE) -> Supplies_and_Materials_Expenses | L80: Semi-Expendable Machinery and Equipment Expenses | M80: =VLOOKUP(L80,[1]links!K$2:L$222,2,FALSE) -> 59 | N80: sewing machine | O80: 1 | P80: 5000 | Q80: 1 | R80: =O80*P80*Q80 -> 5000 | T80: N | U80: Y | V80: N | W80: Direct Payment | AR80: =SUM(AS80:BD80) -> 5000 | AT80: 5000 | BE80: =SUM(BF80:BQ80) -> 5000 | BG80: 5000 | BR80: =SUM(BS80:BU80) -> 0 | BY80: =IF(ISBLANK(C80),0,1) -> 0 | BZ80: =IF(ISBLANK(D80),0,1) -> 0 | CA80: =IF(ISBLANK(F80),0,1) -> 0 | CB80: =IF(ISBLANK(G80),0,1) -> 0 | CC80: =IF(ISBLANK(N80),0,1) -> 1
G81: Conduct procurement of bluetooth speaker for tour guiding offering | H81: No. of procurement of bluetooth speaker for tour guiding offering conducted | K81: =VLOOKUP(J81,links!B$2:C$24,2,FALSE) -> #N/A | R81: =R82 -> 11000 | X81: =SUM(Y81:AD81) -> 0 | AE81: =SUM(AF81:AQ81) -> 1 | AG81: 1 | AR81: =AR82 -> 11000 | AS81: =AS82 -> 0 | AT81: =AT82 -> 11000 | AU81: =AU82 -> 0 | AV81: =AV82 -> 0 | AW81: =AW82 -> 0 | AX81: =AX82 -> 0 | AY81: =AY82 -> 0 | ... BQ81: =BQ82 -> 0 | BR81: =SUM(BR159:BR172) -> 0 | BS81: =SUM(BS159:BS172) -> 0 | BT81: =SUM(BT159:BT172) -> 0 | BU81: =SUM(BU159:BU172) -> 0 | BY81: =IF(ISBLANK(C81),0,1) -> 0 | BZ81: =IF(ISBLANK(D81),0,1) -> 0 | CA81: =IF(ISBLANK(F81),0,1) -> 0 | CB81: =IF(ISBLANK(G81),0,1) -> 1 | CC81: =IF(ISBLANK(N81),0,1) -> 0
I82: MOOE | J82: Supplies and Materials Expenses | K82: =VLOOKUP(J82,[1]links!B$2:C$24,2,FALSE) -> Supplies_and_Materials_Expenses | L82: Information and Communications Technology Equipment | M82: =VLOOKUP(L82,[1]links!K$2:L$222,2,FALSE) -> 62 | N82: bluetooth speaker | O82: 1 | P82: 11000 | Q82: 1 | R82: =O82*P82*Q82 -> 11000 | T82: N | U82: Y | V82: N | W82: Direct Payment | AR82: =SUM(AS82:BD82) -> 11000 | AT82: 11000 | BE82: =SUM(BF82:BQ82) -> 11000 | BG82: 11000 | BR82: =SUM(BS82:BU82) -> 0 | BY82: =IF(ISBLANK(C82),0,1) -> 0 | BZ82: =IF(ISBLANK(D82),0,1) -> 0 | CA82: =IF(ISBLANK(F82),0,1) -> 0 | CB82: =IF(ISBLANK(G82),0,1) -> 0 | CC82: =IF(ISBLANK(N82),0,1) -> 1
G83: Conduct procurement of various tools andequipment for EPAS offering | H83: No. of procurement of various tools and equipment for EPAS offering conducted | K83: =VLOOKUP(J83,links!B$2:C$24,2,FALSE) -> #N/A | R83: =R84 -> 23500 | X83: =SUM(Y83:AD83) -> 0 | AE83: =SUM(AF83:AQ83) -> 1 | AG83: 1 | AR83: =AR84 -> 23500 | AS83: =AS84 -> 0 | AT83: =AT84 -> 23500 | AU83: =AU84 -> 0 | AV83: =AV84 -> 0 | AW83: =AW84 -> 0 | AX83: =AX84 -> 0 | AY83: =AY84 -> 0 | ... BQ83: =BQ84 -> 0 | BR83: =SUM(BR161:BR174) -> 0 | BS83: =SUM(BS161:BS174) -> 0 | BT83: =SUM(BT161:BT174) -> 0 | BU83: =SUM(BU161:BU174) -> 0 | BY83: =IF(ISBLANK(C83),0,1) -> 0 | BZ83: =IF(ISBLANK(D83),0,1) -> 0 | CA83: =IF(ISBLANK(F83),0,1) -> 0 | CB83: =IF(ISBLANK(G83),0,1) -> 1 | CC83: =IF(ISBLANK(N83),0,1) -> 0
I84: MOOE | J84: Supplies and Materials Expenses | K84: =VLOOKUP(J84,[1]links!B$2:C$24,2,FALSE) -> Supplies_and_Materials_Expenses | L84: Other Supplies and Materials Expenses | M84: =VLOOKUP(L84,[1]links!K$2:L$222,2,FALSE) -> 75 | N84: various elecrrical supplies and material | O84: 1 | P84: 23500 | Q84: 1 | R84: =O84*P84*Q84 -> 23500 | T84: N | U84: Y | V84: N | W84: Direct Payment | AR84: =SUM(AS84:BD84) -> 23500 | AT84: 23500 | BE84: =SUM(BF84:BQ84) -> 23500 | BG84: 23500 | BR84: =SUM(BS84:BU84) -> 0 | BY84: =IF(ISBLANK(C84),0,1) -> 0 | BZ84: =IF(ISBLANK(D84),0,1) -> 0 | CA84: =IF(ISBLANK(F84),0,1) -> 0 | CB84: =IF(ISBLANK(G84),0,1) -> 0 | CC84: =IF(ISBLANK(N84),0,1) -> 1
G85: Conduct procurement of various equipment for Cookery offering | H85: No. of procurement of various equipment for Cookery offering conducted | K85: =VLOOKUP(J85,links!B$2:C$24,2,FALSE) -> #N/A | R85: =R86 -> 12000 | X85: =SUM(Y85:AD85) -> 0 | AE85: =SUM(AF85:AQ85) -> 1 | AG85: 1 | AR85: =AR86 -> 12000 | AS85: =AS86 -> 0 | AT85: =AT86 -> 12000 | AU85: =AU86 -> 0 | AV85: =AV86 -> 0 | AW85: =AW86 -> 0 | AX85: =AX86 -> 0 | AY85: =AY86 -> 0 | ... BQ85: =BQ86 -> 0 | BR85: =SUM(BR163:BR176) -> 0 | BS85: =SUM(BS163:BS176) -> 0 | BT85: =SUM(BT163:BT176) -> 0 | BU85: =SUM(BU163:BU176) -> 0 | BY85: =IF(ISBLANK(C85),0,1) -> 0 | BZ85: =IF(ISBLANK(D85),0,1) -> 0 | CA85: =IF(ISBLANK(F85),0,1) -> 0 | CB85: =IF(ISBLANK(G85),0,1) -> 1 | CC85: =IF(ISBLANK(N85),0,1) -> 0
I86: MOOE | J86: Supplies and Materials Expenses | K86: =VLOOKUP(J86,[1]links!B$2:C$24,2,FALSE) -> Supplies_and_Materials_Expenses | L86: Other Machinery and Equipment | M86: =VLOOKUP(L86,[1]links!K$2:L$222,2,FALSE) -> 71 | N86: various equipment for cookery | O86: 1 | P86: 12000 | Q86: 1 | R86: =O86*P86*Q86 -> 12000 | T86: N | U86: Y | V86: N | W86: Direct Payment | AR86: =SUM(AS86:BD86) -> 12000 | AT86: 12000 | BE86: =SUM(BF86:BQ86) -> 12000 | BG86: 12000 | BR86: =SUM(BS86:BU86) -> 0 | BY86: =IF(ISBLANK(C86),0,1) -> 0 | BZ86: =IF(ISBLANK(D86),0,1) -> 0 | CA86: =IF(ISBLANK(F86),0,1) -> 0 | CB86: =IF(ISBLANK(G86),0,1) -> 0 | CC86: =IF(ISBLANK(N86),0,1) -> 1
G87: Conduct procurement other supplies for Cookery offering | H87: No. of procurement other supplies for Cookery offering conducted | K87: =VLOOKUP(J87,links!B$2:C$24,2,FALSE) -> #N/A | R87: =R88 -> 18000 | X87: =SUM(Y87:AD87) -> 0 | AE87: =SUM(AF87:AQ87) -> 1 | AG87: 1 | AR87: =AR88 -> 18000 | AS87: =AS88 -> 0 | AT87: =AT88 -> 18000 | AU87: =AU88 -> 0 | AV87: =AV88 -> 0 | AW87: =AW88 -> 0 | AX87: =AX88 -> 0 | AY87: =AY88 -> 0 | ... BQ87: =BQ88 -> 0 | BR87: =SUM(BR165:BR178) -> 0 | BS87: =SUM(BS165:BS178) -> 0 | BT87: =SUM(BT165:BT178) -> 0 | BU87: =SUM(BU165:BU178) -> 0 | BY87: =IF(ISBLANK(C87),0,1) -> 0 | BZ87: =IF(ISBLANK(D87),0,1) -> 0 | CA87: =IF(ISBLANK(F87),0,1) -> 0 | CB87: =IF(ISBLANK(G87),0,1) -> 1 | CC87: =IF(ISBLANK(N87),0,1) -> 0
I88: MOOE | J88: Supplies and Materials Expenses | K88: =VLOOKUP(J88,[1]links!B$2:C$24,2,FALSE) -> Supplies_and_Materials_Expenses | L88: Other Supplies and Materials Expenses | M88: =VLOOKUP(L88,[1]links!K$2:L$222,2,FALSE) -> 75 | N88: various supplies and materias for cookery offering | O88: 1 | P88: 12000 | Q88: 1 | R88: 18000 | T88: N | U88: Y | V88: N | W88: Direct Payment | AR88: =SUM(AS88:BD88) -> 18000 | AT88: 18000 | BE88: =SUM(BF88:BQ88) -> 18000 | BG88: 18000 | BR88: =SUM(BS88:BU88) -> 0 | BY88: =IF(ISBLANK(C88),0,1) -> 0 | BZ88: =IF(ISBLANK(D88),0,1) -> 0 | CA88: =IF(ISBLANK(F88),0,1) -> 0 | CB88: =IF(ISBLANK(G88),0,1) -> 0 | CC88: =IF(ISBLANK(N88),0,1) -> 1
G89: Conduct procurement of various supplies for hairdressing offering | H89: No. of procurement of various supplies for hairdressing offering conducted | K89: =VLOOKUP(J89,links!B$2:C$24,2,FALSE) -> #N/A | R89: =R90 -> 8500 | X89: =SUM(Y89:AD89) -> 0 | AE89: =SUM(AF89:AQ89) -> 1 | AG89: 1 | AR89: =AR90 -> 8500 | AS89: =AS90 -> 0 | AT89: =AT90 -> 8500 | AU89: =AU90 -> 0 | AV89: =AV90 -> 0 | AW89: =AW90 -> 0 | AX89: =AX90 -> 0 | AY89: =AY90 -> 0 | ... BQ89: =BQ90 -> 0 | BR89: =SUM(BR165:BR178) -> 0 | BS89: =SUM(BS165:BS178) -> 0 | BT89: =SUM(BT165:BT178) -> 0 | BU89: =SUM(BU165:BU178) -> 0 | BY89: =IF(ISBLANK(C89),0,1) -> 0 | BZ89: =IF(ISBLANK(D89),0,1) -> 0 | CA89: =IF(ISBLANK(F89),0,1) -> 0 | CB89: =IF(ISBLANK(G89),0,1) -> 1 | CC89: =IF(ISBLANK(N89),0,1) -> 0
I90: MOOE | J90: Supplies and Materials Expenses | K90: =VLOOKUP(J90,[1]links!B$2:C$24,2,FALSE) -> Supplies_and_Materials_Expenses | L90: Other Supplies and Materials Expenses | M90: =VLOOKUP(L90,[1]links!K$2:L$222,2,FALSE) -> 75 | N90: various supplies for hairdressing | O90: 1 | P90: 8500 | Q90: 1 | R90: =O90*P90*Q90 -> 8500 | T90: N | U90: Y | V90: N | W90: Direct Payment | AR90: =SUM(AS90:BD90) -> 8500 | AT90: 8500 | BE90: =SUM(BF90:BQ90) -> 8500 | BG90: 8500 | BR90: =SUM(BS90:BU90) -> 0 | BY90: =IF(ISBLANK(C90),0,1) -> 0 | BZ90: =IF(ISBLANK(D90),0,1) -> 0 | CA90: =IF(ISBLANK(F90),0,1) -> 0 | CB90: =IF(ISBLANK(G90),0,1) -> 0 | CC90: =IF(ISBLANK(N90),0,1) -> 1
G91: Conduct procurement of various equipment for hairdressing offering | H91: No. of procurement of various equipment for hairdressing offering conducted | K91: =VLOOKUP(J91,links!B$2:C$24,2,FALSE) -> #N/A | R91: =R92 -> 12000 | X91: =SUM(Y91:AD91) -> 0 | AE91: =SUM(AF91:AQ91) -> 1 | AG91: 1 | AR91: =AR92 -> 12000 | AS91: =AS92 -> 0 | AT91: =AT92 -> 12000 | AU91: =AU92 -> 0 | AV91: =AV92 -> 0 | AW91: =AW92 -> 0 | AX91: =AX92 -> 0 | AY91: =AY92 -> 0 | ... BQ91: =BQ92 -> 0 | BR91: =SUM(BR167:BR180) -> 0 | BS91: =SUM(BS167:BS180) -> 0 | BT91: =SUM(BT167:BT180) -> 0 | BU91: =SUM(BU167:BU180) -> 0 | BY91: =IF(ISBLANK(C91),0,1) -> 0 | BZ91: =IF(ISBLANK(D91),0,1) -> 0 | CA91: =IF(ISBLANK(F91),0,1) -> 0 | CB91: =IF(ISBLANK(G91),0,1) -> 1 | CC91: =IF(ISBLANK(N91),0,1) -> 0
I92: MOOE | J92: Supplies and Materials Expenses | K92: =VLOOKUP(J92,[1]links!B$2:C$24,2,FALSE) -> Supplies_and_Materials_Expenses | L92: Other Machinery and Equipment | M92: =VLOOKUP(L92,[1]links!K$2:L$222,2,FALSE) -> 71 | N92: various equipment for hairdressing | O92: 1 | P92: 12000 | Q92: 1 | R92: =O92*P92*Q92 -> 12000 | T92: N | U92: Y | V92: N | W92: Direct Payment | AR92: =SUM(AS92:BD92) -> 12000 | AT92: 12000 | BE92: =SUM(BF92:BQ92) -> 12000 | BG92: 12000 | BR92: =SUM(BS92:BU92) -> 0 | BY92: =IF(ISBLANK(C92),0,1) -> 0 | BZ92: =IF(ISBLANK(D92),0,1) -> 0 | CA92: =IF(ISBLANK(F92),0,1) -> 0 | CB92: =IF(ISBLANK(G92),0,1) -> 0 | CC92: =IF(ISBLANK(N92),0,1) -> 1
C93: Pillar 4:GENDER and Development Program | K93: =VLOOKUP(J93,links!B$2:C$24,2,FALSE) -> #N/A | BY93: =IF(ISBLANK(C93),0,1) -> 1 | BZ93: =IF(ISBLANK(D93),0,1) -> 0 | CA93: =IF(ISBLANK(F93),0,1) -> 0 | CB93: =IF(ISBLANK(G93),0,1) -> 0 | CC93: =IF(ISBLANK(N93),0,1) -> 0
D94: Implemented GAD Program | E94: 17 | H94: No. of Gender and Development Program implemented | K94: =VLOOKUP(J94,links!B$2:C$24,2,FALSE) -> #N/A | X94: =SUM(Y94:AD94) -> 0 | AE94: =SUM(AF94:AQ94) -> 4 | AH94: 1 | AK94: 1 | AN94: 1 | AO94: 1 | BY94: =IF(ISBLANK(C94),0,1) -> 0 | BZ94: =IF(ISBLANK(D94),0,1) -> 1 | CA94: =IF(ISBLANK(F94),0,1) -> 0 | CB94: =IF(ISBLANK(G94),0,1) -> 0 | CC94: =IF(ISBLANK(N94),0,1) -> 0
G95: Conduct procurement of materials and supplies for wellness massage in celebration of Womens' month | H95: No of procurement of materials and supplies for wellness massage in celebration of Womens' month conducted | K95: =VLOOKUP(J95,links!B$2:C$24,2,FALSE) -> #N/A | R95: =R96 -> 7000 | X95: =SUM(Y95:AD95) -> 0 | AE95: =SUM(AF95:AQ95) -> 1 | AH95: 1 | AR95: =AR96 -> 7000 | AS95: =AS96 -> 0 | AT95: =AT96 -> 0 | AU95: =AU96 -> 7000 | AV95: =AV96 -> 0 | AW95: =AW96 -> 0 | AX95: =AX96 -> 0 | AY95: =AY96 -> 0 | ... BQ95: =BQ96 -> 0 | BR95: =SUM(BR171:BR184) -> 0 | BS95: =SUM(BS171:BS184) -> 0 | BT95: =SUM(BT171:BT184) -> 0 | BU95: =SUM(BU171:BU184) -> 0 | BY95: =IF(ISBLANK(C95),0,1) -> 0 | BZ95: =IF(ISBLANK(D95),0,1) -> 0 | CA95: =IF(ISBLANK(F95),0,1) -> 0 | CB95: =IF(ISBLANK(G95),0,1) -> 1 | CC95: =IF(ISBLANK(N95),0,1) -> 0
I96: MOOE | J96: Supplies and Materials Expenses | K96: =VLOOKUP(J96,[1]links!B$2:C$24,2,FALSE) -> Supplies_and_Materials_Expenses | L96: Other Supplies and Materials Expenses | M96: =VLOOKUP(L96,[1]links!K$2:L$222,2,FALSE) -> 75 | N96: welness massage and beauty nail care supplies | O96: 1 | P96: 7000 | Q96: 1 | R96: =O96*P96*Q96 -> 7000 | T96: N | U96: Y | V96: N | W96: Direct Payment | AR96: =SUM(AS96:BD96) -> 7000 | AU96: 7000 | BE96: =SUM(BF96:BQ96) -> 7000 | BH96: 7000 | BR96: =SUM(BS96:BU96) -> 0 | BY96: =IF(ISBLANK(C96),0,1) -> 0 | BZ96: =IF(ISBLANK(D96),0,1) -> 0 | CA96: =IF(ISBLANK(F96),0,1) -> 0 | CB96: =IF(ISBLANK(G96),0,1) -> 0 | CC96: =IF(ISBLANK(N96),0,1) -> 1
G97: Conduct orientation on Magnacarta of Women, Sexual Harrassment in the workplace and Teenage Pregnancy | H97: No.of orientation on Magnacarta of Women, Sexual Harrassment in the workplace and Teenage Pregnancy conducted | K97: =VLOOKUP(J97,links!B$2:C$24,2,FALSE) -> #N/A | R97: =R98 -> 65700 | X97: =SUM(Y97:AD97) -> 0 | AE97: =SUM(AF97:AQ97) -> 1 | AK97: 1 | AR97: =AR98 -> 65700 | AS97: =AS98 -> 0 | AT97: =AT98 -> 0 | AU97: =AU98 -> 0 | AV97: =AV98 -> 0 | AW97: =AW98 -> 0 | AX97: =AX98 -> 65700 | AY97: =AY98 -> 0 | ... BQ97: =BQ98 -> 0 | BR97: =SUM(BR173:BR186) -> 0 | BS97: =SUM(BS173:BS186) -> 0 | BT97: =SUM(BT173:BT186) -> 0 | BU97: =SUM(BU173:BU186) -> 0 | BY97: =IF(ISBLANK(C97),0,1) -> 0 | BZ97: =IF(ISBLANK(D97),0,1) -> 0 | CA97: =IF(ISBLANK(F97),0,1) -> 0 | CB97: =IF(ISBLANK(G97),0,1) -> 1 | CC97: =IF(ISBLANK(N97),0,1) -> 0
I98: MOOE | J98: Training and Scholarship Expenses | K98: =VLOOKUP(J98,[1]links!B$2:C$24,2,FALSE) -> Training_and_Scholarship_Expenses | L98: Training Expenses | M98: =VLOOKUP(L98,[1]links!K$2:L$222,2,FALSE) -> 44 | N98: 2-day training food allowance | O98: 73 | P98: 450 | Q98: 2 | R98: =O98*P98*Q98 -> 65700 | T98: Y | U98: N | V98: N | W98: Direct Payment | AR98: =SUM(AS98:BD98) -> 65700 | AX98: 65700 | BE98: =SUM(BF98:BQ98) -> 65700 | BK98: 65700 | BR98: =SUM(BS98:BU98) -> 0 | BY98: =IF(ISBLANK(C98),0,1) -> 0 | BZ98: =IF(ISBLANK(D98),0,1) -> 0 | CA98: =IF(ISBLANK(F98),0,1) -> 0 | CB98: =IF(ISBLANK(G98),0,1) -> 0 | CC98: =IF(ISBLANK(N98),0,1) -> 1
G99: Conduct orientation on Gender and Development concepts in the classroom/ workplace and Life skills training for women empowerment | H99: No. of orientation on Gender and Development concepts in the classroom/ workplace and Life skills training for women empowerment conducted | K99: =VLOOKUP(J99,links!B$2:C$24,2,FALSE) -> #N/A | R99: =R100 -> 65700 | X99: =SUM(Y99:AD99) -> 0 | AE99: =SUM(AF99:AQ99) -> 1 | AO99: 1 | AR99: =AR100 -> 65700 | AS99: =AS100 -> 0 | AT99: =AT100 -> 0 | AU99: =AU100 -> 0 | AV99: =AV100 -> 0 | AW99: =AW100 -> 0 | AX99: =AX100 -> 0 | AY99: =AY100 -> 0 | ... BQ99: =BQ100 -> 0 | BR99: =SUM(BR175:BR188) -> 0 | BS99: =SUM(BS175:BS188) -> 0 | BT99: =SUM(BT175:BT188) -> 0 | BU99: =SUM(BU175:BU188) -> 0 | BY99: =IF(ISBLANK(C99),0,1) -> 0 | BZ99: =IF(ISBLANK(D99),0,1) -> 0 | CA99: =IF(ISBLANK(F99),0,1) -> 0 | CB99: =IF(ISBLANK(G99),0,1) -> 1 | CC99: =IF(ISBLANK(N99),0,1) -> 0
I100: MOOE | J100: Training and Scholarship Expenses | K100: =VLOOKUP(J100,[1]links!B$2:C$24,2,FALSE) -> Training_and_Scholarship_Expenses | L100: Training Expenses | M100: =VLOOKUP(L100,[1]links!K$2:L$222,2,FALSE) -> 44 | N100: snacks during the conduct of training | O100: 73 | P100: 450 | Q100: 2 | R100: =O100*P100*Q100 -> 65700 | T100: Y | U100: N | V100: N | W100: Direct Payment | AR100: =SUM(AS100:BD100) -> 65700 | BB100: 65700 | BE100: =SUM(BF100:BQ100) -> 65700 | BO100: 65700 | BR100: =SUM(BS100:BU100) -> 0 | BY100: =IF(ISBLANK(C100),0,1) -> 0 | BZ100: =IF(ISBLANK(D100),0,1) -> 0 | CA100: =IF(ISBLANK(F100),0,1) -> 0 | CB100: =IF(ISBLANK(G100),0,1) -> 0 | CC100: =IF(ISBLANK(N100),0,1) -> 1
G101: Conduct orientation on violence against women and children | H101: No. of orientation on violence against women and children conducted | K101: =VLOOKUP(J101,links!B$2:C$24,2,FALSE) -> #N/A | R101: =R102 -> 16060 | X101: =SUM(Y101:AD101) -> 0 | AE101: =SUM(AF101:AQ101) -> 1 | AP101: 1 | AR101: =AR102 -> 16060 | AS101: =AS102 -> 0 | AT101: =AT102 -> 0 | AU101: =AU102 -> 0 | AV101: =AV102 -> 0 | AW101: =AW102 -> 0 | AX101: =AX102 -> 0 | AY101: =AY102 -> 0 | ... BQ101: =BQ102 -> 0 | BR101: =SUM(BR177:BR190) -> 0 | BS101: =SUM(BS177:BS190) -> 0 | BT101: =SUM(BT177:BT190) -> 0 | BU101: =SUM(BU177:BU190) -> 0 | BY101: =IF(ISBLANK(C101),0,1) -> 0 | BZ101: =IF(ISBLANK(D101),0,1) -> 0 | CA101: =IF(ISBLANK(F101),0,1) -> 0 | CB101: =IF(ISBLANK(G101),0,1) -> 1 | CC101: =IF(ISBLANK(N101),0,1) -> 0
I102: MOOE | J102: Training and Scholarship Expenses | K102: =VLOOKUP(J102,[1]links!B$2:C$24,2,FALSE) -> Training_and_Scholarship_Expenses | L102: Training Expenses | M102: =VLOOKUP(L102,[1]links!K$2:L$222,2,FALSE) -> 44 | N102: snacks during the conduct of training | O102: 73 | P102: 220 | Q102: 1 | R102: =O102*P102*Q102 -> 16060 | T102: Y | U102: N | V102: N | W102: Direct Payment | AR102: =SUM(AS102:BD102) -> 16060 | BC102: 16060 | BE102: =SUM(BF102:BQ102) -> 16060 | BP102: 16060 | BR102: =SUM(BS102:BU102) -> 0 | BY102: =IF(ISBLANK(C102),0,1) -> 0 | BZ102: =IF(ISBLANK(D102),0,1) -> 0 | CA102: =IF(ISBLANK(F102),0,1) -> 0 | CB102: =IF(ISBLANK(G102),0,1) -> 0 | CC102: =IF(ISBLANK(N102),0,1) -> 1
C103: Pillar 5:PRO- Project Repair and Orderliness | K103: =VLOOKUP(J103,links!B$2:C$24,2,FALSE) -> #N/A | BY103: =IF(ISBLANK(C103),0,1) -> 1 | BZ103: =IF(ISBLANK(D103),0,1) -> 0 | CA103: =IF(ISBLANK(F103),0,1) -> 0 | CB103: =IF(ISBLANK(G103),0,1) -> 0 | CC103: =IF(ISBLANK(N103),0,1) -> 0
...

Sheet links
A1: expense_class | B1: object_group | F1: id | G1: Expense_Class | H1: object_expenditure_uacs | I1: object_group | J1: object_code | K1: object_expenditure_desc | L1: id | M1: PS | N1: GASS | O1: For Downloading (Board and Lodging) | P1: Y
A2: CO | B2: Intangible Assets Outlay | C2: Intangible_Assets_Outlay | F2: 1 | G2: PS | H2: 5010101001 | I2: Salaries and Wages | J2: Salaries and Wages - Regular | K2: Salaries and Wages - Regular | L2: 1 | M2: MOOE | N2: STO | O2: For Downloading (Program Support Fund) | P2: N
A3: CO | B3: Property, Plant and Equipment Outlay | C3: Property__Plant_and_Equipment_Outlay | F3: 2 | G3: PS | H3: 5010102000 | I3: Salaries and Wages | J3: Salaries and Wages - Casual/Contractual | K3: Salaries and Wages - Casual/Contractual | L3: 2 | M3: CO | N3: Operation | O3: Direct Payment
A4: MOOE | B4: Awards/Rewards and Prizes | C4: Awards_Rewards_and_Prizes | F4: 3 | G4: PS | H4: 5010201001 | I4: Other Compensation | J4: Personal Economic Relief Allowance (PERA) | K4: PERA - Civilian | L4: 3 | O4: Cash Advance
A5: MOOE | B5: Communication Expenses | C5: Communication_Expenses | F5: 4 | G5: PS | H5: 5010202000 | I5: Other Compensation | J5: Representation Allowance (RA) | K5: Representation Allowance (RA) | L5: 4 | O5: Fund Transfer to Other Agency
A6: MOOE | B6: Confidential, Intelligence and Extraordinary Expenses | C6: Confidential__Intelligence_and_Extraordinary_Expenses | F6: 5 | G6: PS | H6: 5010203001 | I6: Other Compensation | J6: Transportation Allowance (TA) | K6: Transportation Allowance (TA) | L6: 5
A7: MOOE | B7: Demolition/Relocation and Desilting/Dredging Expenses | C7: Demolition_Relocation_and_Desilting_Dredging_Expenses | F7: 6 | G7: PS | H7: 5010204001 | I7: Other Compensation | J7: Clothing/Uniform Allowance | K7: Clothing/Uniform Allowance - Civilian | L7: 6
A8: MOOE | B8: Financial Assistance/Subsidy | C8: Financial_Assistance_Subsidy | F8: 7 | G8: PS | H8: 5010205003 | I8: Other Compensation | J8: Subsistence Allowance (SA) | K8: Subsistence Allowance - Magna Carta for Public Health Workers under R.A. 7305 | L8: 7
A9: MOOE | B9: General Services | C9: General_Services | F9: 8 | G9: PS | H9: 5010206004 | I9: Other Compensation | J9: Laundry Allowance ( LA ) | K9: Laundry Allowance - Magna Carta Benefits for Public Health Workers under R.A. 7305 | L9: 8
A10: MOOE | B10: Generation, Transmission and Distribution Expenses | C10: Generation__Transmission_and_Distribution_Expenses | F10: 9 | G10: PS | H10: 5010207001 | I10: Other Compensation | J10: Quarters Allowance ( QA ) | K10: Quarters Allowance - Civilian | L10: 9
A11: MOOE | B11: Labor and Wages | C11: Labor_and_Wages | F11: 10 | G11: PS | H11: 5010207004 | I11: Other Compensation | J11: Quarters Allowance ( QA ) | K11: Quarters Allowance - Magna Carta Benefits for Public Health Workers under R.A. 7305 | L11: 10
A12: MOOE | B12: Other Maintenance and Operating Expenses | C12: Other_Maintenance_and_Operating_Expenses | F12: 11 | G12: PS | H12: 5010208001 | I12: Other Compensation | J12: Productivity Incentive Allowance (PIA) | K12: Productivity Incentive Allowance - Civilian | L12: 11
A13: MOOE | B13: Professional Services | C13: Professional_Services | F13: 12 | G13: PS | H13: 5010210001 | I13: Other Compensation | J13: Honoraria | K13: Honoraria - Civilian | L13: 12
A14: MOOE | B14: Repairs and Maintenance | C14: Repairs_and_Maintenance | F14: 13 | G14: PS | H14: 5010211002 | I14: Other Compensation | J14: Hazard Pay ( HP ) | K14: Hazard Duty Pay - Civilian | L14: 13
A15: MOOE | B15: Supplies and Materials Expenses | C15: Supplies_and_Materials_Expenses | F15: 14 | G15: PS | H15: 5010211005 | I15: Other Compensation | J15: Hazard Pay ( HP ) | K15: HP - Magna Carta Benefits for Public Health Workers under R.A. 7305 | L15: 14
A16: MOOE | B16: Survey, Research, Exploration and Development Expenses | C16: Survey__Research__Exploration_and_Development_Expenses | F16: 15 | G16: PS | H16: 5010212001 | I16: Other Compensation | J16: Longevity Pay ( LP ) | K16: Longevity Pay - Civilian | L16: 15
A17: MOOE | B17: Taxes, Insurance Premiums and Other Fees | C17: Taxes__Insurance_Premiums_and_Other_Fees | F17: 16 | G17: PS | H17: 5010213001 | I17: Other Compensation | J17: Overtime and Night Pay | K17: Overtime Pay | L17: 16
... A24: PS | B24: Salaries and Wages | C24: Salaries_and_Wages | F24: 23 | G24: PS | H24: 5010299036 | I24: Other Compensation | J24: Other Bonuses and Allowances | K24: Mid-Year Bonus - Civilian | L24: 23
F25: 24 | G25: PS | H25: 5010299038 | I25: Other Compensation | J25: Other Bonuses and Allowances | K25: Anniversary Bonus - Civilian | L25: 24
F26: 25 | G26: PS | H26: 5010301000 | I26: Personnel Benefit Contributions | J26: Retirement and Life Insurance Premiums | K26: Retirement and Life Insurance Premiums | L26: 25
F27: 26 | G27: PS | H27: 5010302001 | I27: Personnel Benefit Contributions | J27: Pag-IBIG Contributions | K27: Pag-IBIG - Civilian | L27: 26
F28: 27 | G28: PS | H28: 5010303001 | I28: Personnel Benefit Contributions | J28: PhilHealth Contributions | K28: PhilHealth - Civilian | L28: 27
F29: 28 | G29: PS | H29: 5010304001 | I29: Personnel Benefit Contributions | J29: Employees Compensation Insurance Premiums (ECIP) | K29: ECIP - Civilian | L29: 28
F30: 29 | G30: PS | H30: 5010402001 | I30: Other Personnel Benefits | J30: Retirement Gratuity | K30: Retirement Gratuity - Civilian | L30: 29
F31: 30 | G31: PS | H31: 5010403001 | I31: Other Personnel Benefits | J31: Terminal Leave Benefits | K31: Terminal Leave Benefits - Civilian | L31: 30
F32: 31 | G32: PS | H32: 5010499001 | I32: Other Personnel Benefits | J32: Other Personnel Benefits | K32: Lump-sum for Creation of New Positions - Civilian | L32: 31
F33: 32 | G33: PS | H33: 5010499003 | I33: Other Personnel Benefits | J33: Other Personnel Benefits | K33: Lump-sum for Reclassification of Positions | L33: 32
F34: 33 | G34: PS | H34: 5010499004 | I34: Other Personnel Benefits | J34: Other Personnel Benefits | K34: Lump-sum for Equivalent-Record Form | L34: 33
F35: 34 | G35: PS | H35: 5010499005 | I35: Other Personnel Benefits | J35: Other Personnel Benefits | K35: Lump-sum for Master Teachers | L35: 34
F36: 35 | G36: PS | H36: 5010499006 | I36: Other Personnel Benefits | J36: Other Personnel Benefits | K36: Lump-sum for Compensation Adjustment | L36: 35
... F222: 221 | G222: CO | H222: 5060699000 | I222: Intangible Assets Outlay | J222: Other Intangible Assets | K222: Other Intangible Assets | L222: 221
